[{"class_name": "king", "bbox": "357 66 419 211", "used": true}, {"class_name": "king", "bbox": "390 156 460 273", "used": true}, {"class_name": "queen", "bbox": "531 210 592 332", "used": true}, {"class_name": "queen", "bbox": "673 249 747 371", "used": true}, {"class_name": "king", "bbox": "328 252 399 388", "used": true}, {"class_name": "king", "bbox": "730 320 812 458", "used": true}, {"class_name": "king", "bbox": "256 388 336 522", "used": true}, {"class_name": "queen", "bbox": "693 467 765 574", "used": true}, {"class_name": "queen", "bbox": "309 492 377 613", "used": true}, {"class_name": "queen", "bbox": "442 580 507 685", "used": true}, {"class_name": "king", "bbox": "622 605 697 724", "used": true}, {"class_name": "queen", "bbox": "691 729 778 851", "used": true}]