[{"class_name": "queen", "bbox": "573 61 644 188", "used": true}, {"class_name": "king", "bbox": "562 161 625 273", "used": true}, {"class_name": "queen", "bbox": "427 229 497 334", "used": true}, {"class_name": "queen", "bbox": "683 260 741 366", "used": true}, {"class_name": "king", "bbox": "295 278 369 408", "used": true}, {"class_name": "queen", "bbox": "746 373 823 491", "used": true}, {"class_name": "queen", "bbox": "270 388 349 505", "used": true}, {"class_name": "king", "bbox": "739 462 822 591", "used": true}, {"class_name": "queen", "bbox": "371 516 441 627", "used": true}, {"class_name": "king", "bbox": "593 570 669 685", "used": true}, {"class_name": "king", "bbox": "453 660 520 763", "used": true}, {"class_name": "king", "bbox": "423 788 497 899", "used": true}]